targeted_causal_reduction/__init__.py
targeted_causal_reduction/__main__.py
targeted_causal_reduction/config.py
targeted_causal_reduction/parser.py
targeted_causal_reduction/causal_model/__init__.py
targeted_causal_reduction/causal_model/high_level.py
targeted_causal_reduction/causal_model/low_level.py
targeted_causal_reduction/data_generators/__init__.py
targeted_causal_reduction/data_generators/linear.py
targeted_causal_reduction/data_generators/mass_spring.py
targeted_causal_reduction/data_generators/n_well/__init__.py
targeted_causal_reduction/data_generators/n_well/base.py
targeted_causal_reduction/data_generators/n_well/double_well.py
targeted_causal_reduction/data_generators/n_well/triple_well.py
targeted_causal_reduction/data_generators/processing/__init__.py
targeted_causal_reduction/data_generators/processing/core.py
targeted_causal_reduction/data_generators/processing/disk.py
targeted_causal_reduction/data_generators/processing/hdf5_dataset.py
targeted_causal_reduction/data_generators/processing/in_memory.py
targeted_causal_reduction/lightning/__init__.py
targeted_causal_reduction/lightning/targeted_causal_reduction.py
targeted_causal_reduction/lightning/utils.py
targeted_causal_reduction/reduction/__init__.py
targeted_causal_reduction/reduction/reduction.py
targeted_causal_reduction/reduction/reduction_map.py
targeted_causal_reduction/simulator/__init__.py
targeted_causal_reduction/simulator/simulator.py
targeted_causal_reduction-0.0.1a1.dist-info/LICENSE
targeted_causal_reduction-0.0.1a1.dist-info/METADATA
targeted_causal_reduction-0.0.1a1.dist-info/WHEEL
targeted_causal_reduction-0.0.1a1.dist-info/entry_points.txt
targeted_causal_reduction-0.0.1a1.dist-info/top_level.txt
targeted_causal_reduction-0.0.1a1.dist-info/RECORD
