Metadata-Version: 2.1
Name: targeted-causal-reduction
Version: 0.0.1a1
Summary: Targeted causal reduction learns high-level causes for phenomena occuring in simulations.
Author-email: Armin Kekic <armin.kekic@mailbox.org>
License: MIT
Project-URL: source, https://github.com/akekic/targeted-causal-reduction
Requires-Python: >=3.11
License-File: LICENSE
Requires-Dist: h5py
Requires-Dist: lightning
Requires-Dist: matplotlib
Requires-Dist: numpy
Requires-Dist: scikit-learn
Requires-Dist: scipy
Requires-Dist: typed-argument-parser
Requires-Dist: wandb
Provides-Extra: dev
Requires-Dist: pytest ; extra == 'dev'
